datacommons/__init__.py
datacommons/core.py
datacommons/places.py
datacommons/populations.py
datacommons/query.py
datacommons/stat_vars.py
datacommons/utils.py
datacommons_pandas/__init__.py
datacommons_pandas/core.py
datacommons_pandas/df_builder.py
datacommons_pandas/places.py
datacommons_pandas/populations.py
datacommons_pandas/query.py
datacommons_pandas/stat_vars.py
datacommons_pandas/utils.py
datacommons_pandas-0.0.3.dist-info/LICENSE
datacommons_pandas-0.0.3.dist-info/METADATA
datacommons_pandas-0.0.3.dist-info/WHEEL
datacommons_pandas-0.0.3.dist-info/top_level.txt
datacommons_pandas-0.0.3.dist-info/RECORD
