Metadata-Version: 2.1
Name: datacommons_pandas
Version: 0.0.3
Summary: A library to create pandas objects using the Data Commons Python API.
Home-page: https://github.com/datacommonsorg/api-python
Author: datacommons.org
Author-email: support@datacommons.org
Maintainer: datacommons.org
Maintainer-email: support@datacommons.org
License: Apache 2.0
Platform: UNKNOWN
Classifier: Intended Audience :: Developers
Classifier: License :: OSI Approved :: Apache Software License
Classifier: Programming Language :: Python
Classifier: Programming Language :: Python :: 2.7
Classifier: Programming Language :: Python :: 3.6
Classifier: Programming Language :: Python :: Implementation :: CPython
Classifier: Topic :: Software Development
Requires-Python: >=2.7
